pytruffle/__init__.py
pytruffle/test/__init__.py
pytruffle/test/test_haystack.py
pytruffle/test/test_main.py
pytruffle-0.1.1.dist-info/METADATA
pytruffle-0.1.1.dist-info/WHEEL
pytruffle-0.1.1.dist-info/licenses/LICENSE
pytruffle-0.1.1.dist-info/RECORD
