Metadata-Version: 2.4
Name: pytruffle
Version: 0.1.1
Summary: Block-level Code Retrieval using LLMs
Author-email: Gerhard Stenzel <gerhard.stenzel@ifi.lmu.de>
License: MIT
License-File: LICENSE
Classifier: Operating System :: OS Independent
Classifier: Programming Language :: Python :: 3
Requires-Python: >=3.12
Requires-Dist: jinja2>=3.1.5
Requires-Dist: openai>=1.58.1
Requires-Dist: pydantic>=2.10.4
Provides-Extra: haystack
Requires-Dist: haystack-ai>=2.8.0; extra == 'haystack'
